bounded_subprocess/__init__.py
bounded_subprocess/bounded_subprocess.py
bounded_subprocess/bounded_subprocess_async.py
bounded_subprocess/interactive.py
bounded_subprocess/interactive_async.py
bounded_subprocess/util.py
bounded_subprocess-2.5.0.dist-info/METADATA
bounded_subprocess-2.5.0.dist-info/WHEEL
bounded_subprocess-2.5.0.dist-info/licenses/LICENSE.txt
bounded_subprocess-2.5.0.dist-info/RECORD
