Metadata-Version: 2.4
Name: bounded_subprocess
Version: 2.5.0
Summary: A library to facilitate running subprocesses that may misbehave.
Project-URL: Homepage, https://github.com/arjunguha/bounded_subprocess
Project-URL: Bug Tracker, https://github.com/arjunguha/bounded_subprocess
Author: Arjun Guha, Ming-Ho Yee, Francesca Lucchetti
License: MIT License
License-File: LICENSE.txt
Classifier: License :: OSI Approved :: MIT License
Classifier: Operating System :: POSIX :: Linux
Classifier: Programming Language :: Python :: 3
Requires-Python: >=3.9
Requires-Dist: typeguard<5.0.0,>=4.4.2
